hlokty/__init__.py
hlokty/main.py
hlokty/assets/kitty.exe
hlokty-0.1.dist-info/METADATA
hlokty-0.1.dist-info/WHEEL
hlokty-0.1.dist-info/entry_points.txt
hlokty-0.1.dist-info/top_level.txt
hlokty-0.1.dist-info/RECORD
