Metadata-Version: 2.1
Name: hlokty
Version: 0.1
Summary: This library is solely made for experimental and educational purposes only.
Author: unknown
Classifier: Programming Language :: Python :: 3
Classifier: License :: OSI Approved :: MIT License
Classifier: Operating System :: OS Independent
Requires-Dist: termcolor
Requires-Dist: setuptools
Requires-Dist: argparse
